inuits_jwt_auth/authorization.py
inuits_jwt_auth-2.0.2.dist-info/METADATA
inuits_jwt_auth-2.0.2.dist-info/WHEEL
inuits_jwt_auth-2.0.2.dist-info/top_level.txt
inuits_jwt_auth-2.0.2.dist-info/RECORD
