Metadata-Version: 2.1
Name: inuits-jwt-auth
Version: 2.0.2
Summary: A small library to handle JWT auth including roles and permissions
Author: Inuits
Author-email: developers@inuits.eu
License: GPLv2
Classifier: License :: OSI Approved :: GNU General Public License v2 (GPLv2)
Classifier: Intended Audience :: Developers
Classifier: Programming Language :: Python :: 3
Provides: inuits_jwt_auth
Requires-Dist: Authlib (>=1.2.0)
Requires-Dist: cryptography (>=39.0.0)
Requires-Dist: Flask (>=2.2.2)
Requires-Dist: requests (>=2.28.2)
Requires-Dist: Werkzeug (>=2.2.2)
